resonator_tools/__init__.py
resonator_tools/calibration.py
resonator_tools/circlefit.py
resonator_tools/circuit.py
resonator_tools/noise.py
resonator_tools/utilities.py
resonator_tools_vdrhtc-0.13.dist-info/licenses/LICENSE
resonator_tools_vdrhtc-0.13.dist-info/METADATA
resonator_tools_vdrhtc-0.13.dist-info/WHEEL
resonator_tools_vdrhtc-0.13.dist-info/top_level.txt
resonator_tools_vdrhtc-0.13.dist-info/RECORD
