Metadata-Version: 2.4
Name: resonator_tools_vdrhtc
Version: 0.13
Summary: resonator_tools fork from vdrhtc
Home-page: https://github.com/vdrhtc/resonator_tools
Download-URL: https://github.com/vdrhtc/resonator_tools
Author: Sebastian Probst
Author-email: seb.probst@gmail.com
License-File: LICENSE
Requires-Dist: nose
Dynamic: author
Dynamic: author-email
Dynamic: download-url
Dynamic: home-page
Dynamic: license-file
Dynamic: requires-dist
Dynamic: summary
